betamax/__init__.py
betamax/adapter.py
betamax/configure.py
betamax/decorator.py
betamax/exceptions.py
betamax/headers.py
betamax/mock_response.py
betamax/options.py
betamax/recorder.py
betamax/util.py
betamax/cassette/__init__.py
betamax/cassette/cassette.py
betamax/cassette/interaction.py
betamax/fixtures/__init__.py
betamax/fixtures/pytest.py
betamax/fixtures/unittest.py
betamax/matchers/__init__.py
betamax/matchers/base.py
betamax/matchers/body.py
betamax/matchers/digest_auth.py
betamax/matchers/headers.py
betamax/matchers/host.py
betamax/matchers/method.py
betamax/matchers/path.py
betamax/matchers/query.py
betamax/matchers/uri.py
betamax/serializers/__init__.py
betamax/serializers/base.py
betamax/serializers/json_serializer.py
betamax/serializers/proxy.py
betamax-0.9.0.dist-info/LICENSE
betamax-0.9.0.dist-info/METADATA
betamax-0.9.0.dist-info/WHEEL
betamax-0.9.0.dist-info/entry_points.txt
betamax-0.9.0.dist-info/top_level.txt
betamax-0.9.0.dist-info/RECORD
